python_xfoil/__init__.py
python_xfoil/xfoil.py
python_xfoil-0.1.0.dist-info/licenses/LICENSE
python_xfoil-0.1.0.dist-info/METADATA
python_xfoil-0.1.0.dist-info/WHEEL
python_xfoil-0.1.0.dist-info/top_level.txt
python_xfoil-0.1.0.dist-info/RECORD
