Metadata-Version: 2.4
Name: python-xfoil
Version: 0.1.0
Summary: A Python interface for XFOIL aerodynamic analysis
Home-page: https://github.com/cc-aero/pythonxfoil
Author: cc-aero
Author-email: 
License: MIT
Project-URL: Homepage, https://github.com/cc-aero/pythonxfoil
Project-URL: Bug Tracker, https://github.com/cc-aero/pythonxfoil/issues
Classifier: Programming Language :: Python :: 3
Classifier: License :: OSI Approved :: MIT License
Classifier: Operating System :: OS Independent
Classifier: Topic :: Scientific/Engineering :: Physics
Classifier: Topic :: Scientific/Engineering :: Visualization
Requires-Python: >=3.6
License-File: LICENSE
Dynamic: home-page
Dynamic: license-file
Dynamic: requires-python
